{
	"song": {
		"player1": "bf",
		"player2": "brick",
		"notes": [
			{
				"lengthInSteps": 16,
				"sectionNotes": [],
				"mustHitSection": false
			},
			{
				"lengthInSteps": 16,
				"sectionNotes": [],
				"mustHitSection": true
			},
			{
				"lengthInSteps": 16,
				"sectionNotes": [],
				"mustHitSection": false
			},
			{
				"lengthInSteps": 16,
				"sectionNotes": [],
				"mustHitSection": false
			},
			{
				"lengthInSteps": 16,
				"sectionNotes": [],
				"mustHitSection": true
			},
			{
				"lengthInSteps": 16,
				"sectionNotes": [],
				"mustHitSection": true
			},
			{
				"lengthInSteps": 16,
				"sectionNotes": [],
				"mustHitSection": false
			},
			{
				"lengthInSteps": 16,
				"sectionNotes": [],
				"mustHitSection": false
			},
			{
				"lengthInSteps": 16,
				"sectionNotes": [],
				"mustHitSection": true
			},
			{
				"lengthInSteps": 16,
				"sectionNotes": [],
				"mustHitSection": true
			},
			{
				"lengthInSteps": 16,
				"sectionNotes": [],
				"mustHitSection": false
			},
			{
				"lengthInSteps": 16,
				"sectionNotes": [],
				"mustHitSection": false
			},
			{
				"lengthInSteps": 16,
				"sectionNotes": [
					[
						14550,
						6,
						0
					],
					[
						14700,
						4,
						0
					],
					[
						14850,
						7,
						0
					],
					[
						15000,
						5,
						525
					]
				],
				"mustHitSection": true
			},
			{
				"lengthInSteps": 16,
				"sectionNotes": [
					[
						15750,
						7,
						0
					],
					[
						15900,
						4,
						0
					],
					[
						16050,
						7,
						0
					],
					[
						16200,
						6,
						525
					]
				],
				"mustHitSection": true
			},
			{
				"lengthInSteps": 16,
				"sectionNotes": [
					[
						16950,
						2,
						0
					],
					[
						17100,
						0,
						0
					],
					[
						17250,
						3,
						0
					],
					[
						17400,
						2,
						0
					],
					[
						17550,
						1,
						0
					],
					[
						17700,
						0,
						0
					],
					[
						17850,
						2,
						0
					]
				],
				"mustHitSection": false
			},
			{
				"lengthInSteps": 16,
				"sectionNotes": [
					[
						18000,
						3,
						0
					],
					[
						18150,
						0,
						0
					],
					[
						18450,
						1,
						0
					],
					[
						18600,
						2,
						525
					]
				],
				"mustHitSection": false
			},
			{
				"lengthInSteps": 16,
				"sectionNotes": [
					[
						19350,
						0,
						0
					],
					[
						19350,
						4,
						0
					],
					[
						19500,
						3,
						0
					],
					[
						19500,
						7,
						0
					],
					[
						19650,
						0,
						0
					],
					[
						19650,
						4,
						0
					],
					[
						19800,
						2,
						0
					],
					[
						19800,
						6,
						0
					],
					[
						19950,
						1,
						0
					],
					[
						19950,
						5,
						0
					],
					[
						20100,
						0,
						0
					],
					[
						20100,
						4,
						0
					],
					[
						20250,
						2,
						0
					],
					[
						20250,
						6,
						0
					]
				],
				"mustHitSection": true
			},
			{
				"lengthInSteps": 16,
				"sectionNotes": [
					[
						20400,
						1,
						225
					],
					[
						20400,
						5,
						225
					],
					[
						20850,
						2,
						0
					],
					[
						20850,
						6,
						0
					],
					[
						21000,
						3,
						0
					],
					[
						21000,
						7,
						0
					],
					[
						21150,
						0,
						0
					],
					[
						21150,
						4,
						0
					],
					[
						21450,
						1,
						225
					],
					[
						21450,
						5,
						225
					]
				],
				"mustHitSection": true
			},
			{
				"lengthInSteps": 16,
				"sectionNotes": [
					[
						21750,
						3,
						0
					],
					[
						21750,
						7,
						0
					],
					[
						21900,
						2,
						0
					],
					[
						21900,
						6,
						0
					],
					[
						22050,
						3,
						0
					],
					[
						22050,
						7,
						0
					],
					[
						22200,
						0,
						0
					],
					[
						22200,
						4,
						0
					],
					[
						22350,
						1,
						0
					],
					[
						22350,
						5,
						0
					],
					[
						22500,
						3,
						0
					],
					[
						22500,
						7,
						0
					],
					[
						22650,
						2,
						0
					],
					[
						22650,
						6,
						0
					]
				],
				"mustHitSection": false
			},
			{
				"lengthInSteps": 16,
				"sectionNotes": [
					[
						22800,
						5,
						0
					],
					[
						22800,
						1,
						0
					],
					[
						22950,
						6,
						0
					],
					[
						22950,
						2,
						0
					],
					[
						23250,
						0,
						0
					],
					[
						23250,
						4,
						0
					],
					[
						23400,
						3,
						375
					],
					[
						23400,
						7,
						375
					]
				],
				"mustHitSection": false
			},
			{
				"lengthInSteps": 16,
				"sectionNotes": [
					[
						24150,
						6,
						0
					],
					[
						24300,
						4,
						0
					],
					[
						24450,
						7,
						0
					],
					[
						24600,
						5,
						525
					]
				],
				"mustHitSection": true
			},
			{
				"lengthInSteps": 16,
				"sectionNotes": [
					[
						25350,
						7,
						0
					],
					[
						25500,
						4,
						0
					],
					[
						25650,
						7,
						0
					],
					[
						25800,
						6,
						525
					]
				],
				"mustHitSection": true
			},
			{
				"lengthInSteps": 16,
				"sectionNotes": [
					[
						26550,
						2,
						0
					],
					[
						26700,
						0,
						0
					],
					[
						26850,
						3,
						0
					],
					[
						27000,
						2,
						0
					],
					[
						27150,
						1,
						0
					],
					[
						27300,
						0,
						0
					],
					[
						27450,
						2,
						0
					]
				],
				"mustHitSection": false
			},
			{
				"lengthInSteps": 16,
				"sectionNotes": [
					[
						27600,
						3,
						0
					],
					[
						27750,
						0,
						0
					],
					[
						28050,
						1,
						0
					],
					[
						28200,
						2,
						525
					]
				],
				"mustHitSection": false
			},
			{
				"lengthInSteps": 16,
				"sectionNotes": [
					[
						28950,
						0,
						0
					],
					[
						28950,
						4,
						0
					],
					[
						29100,
						3,
						0
					],
					[
						29100,
						7,
						0
					],
					[
						29250,
						0,
						0
					],
					[
						29250,
						4,
						0
					],
					[
						29400,
						2,
						0
					],
					[
						29400,
						6,
						0
					],
					[
						29550,
						1,
						0
					],
					[
						29550,
						5,
						0
					],
					[
						29700,
						0,
						0
					],
					[
						29700,
						4,
						0
					],
					[
						29850,
						2,
						0
					],
					[
						29850,
						6,
						0
					]
				],
				"mustHitSection": true
			},
			{
				"lengthInSteps": 16,
				"sectionNotes": [
					[
						30000,
						1,
						225
					],
					[
						30000,
						5,
						225
					],
					[
						30450,
						2,
						0
					],
					[
						30450,
						6,
						0
					],
					[
						30600,
						3,
						0
					],
					[
						30600,
						7,
						0
					],
					[
						30750,
						0,
						0
					],
					[
						30750,
						4,
						0
					],
					[
						31050,
						1,
						225
					],
					[
						31050,
						5,
						225
					]
				],
				"mustHitSection": true
			},
			{
				"lengthInSteps": 16,
				"sectionNotes": [
					[
						31350,
						3,
						0
					],
					[
						31350,
						7,
						0
					],
					[
						31500,
						2,
						0
					],
					[
						31500,
						6,
						0
					],
					[
						31650,
						3,
						0
					],
					[
						31650,
						7,
						0
					],
					[
						31800,
						0,
						0
					],
					[
						31800,
						4,
						0
					],
					[
						31950,
						1,
						0
					],
					[
						31950,
						5,
						0
					],
					[
						32100,
						3,
						0
					],
					[
						32100,
						7,
						0
					],
					[
						32250,
						2,
						0
					],
					[
						32250,
						6,
						0
					]
				],
				"mustHitSection": false
			},
			{
				"lengthInSteps": 16,
				"sectionNotes": [
					[
						32400,
						5,
						0
					],
					[
						32400,
						1,
						0
					],
					[
						32550,
						6,
						0
					],
					[
						32550,
						2,
						0
					],
					[
						32850,
						0,
						0
					],
					[
						32850,
						4,
						0
					],
					[
						33000,
						7,
						375
					],
					[
						33000,
						1,
						1725
					]
				],
				"mustHitSection": false
			},
			{
				"lengthInSteps": 16,
				"sectionNotes": [
					[
						34200,
						2,
						525
					],
					[
						34200,
						6,
						525
					]
				],
				"mustHitSection": true
			},
			{
				"lengthInSteps": 16,
				"sectionNotes": [
					[
						34800,
						7,
						525
					],
					[
						34800,
						3,
						525
					],
					[
						35400,
						4,
						375
					],
					[
						35400,
						0,
						375
					],
					[
						35850,
						5,
						675
					],
					[
						35850,
						1,
						675
					]
				],
				"mustHitSection": true
			},
			{
				"lengthInSteps": 16,
				"sectionNotes": [
					[
						36600,
						6,
						525
					],
					[
						36600,
						2,
						525
					]
				],
				"mustHitSection": false
			},
			{
				"lengthInSteps": 16,
				"sectionNotes": [
					[
						37200,
						7,
						525
					],
					[
						37200,
						3,
						525
					],
					[
						37800,
						4,
						75
					],
					[
						37800,
						0,
						75
					],
					[
						38250,
						5,
						675
					],
					[
						38250,
						1,
						675
					],
					[
						38100,
						4,
						0
					],
					[
						38100,
						0,
						0
					]
				],
				"mustHitSection": false
			},
			{
				"lengthInSteps": 16,
				"sectionNotes": [
					[
						39000,
						2,
						525
					],
					[
						39000,
						6,
						525
					]
				],
				"mustHitSection": true
			},
			{
				"lengthInSteps": 16,
				"sectionNotes": [
					[
						39600,
						7,
						525
					],
					[
						39600,
						3,
						525
					],
					[
						40200,
						4,
						525
					],
					[
						40200,
						0,
						525
					]
				],
				"mustHitSection": true
			},
			{
				"lengthInSteps": 16,
				"sectionNotes": [
					[
						40800,
						6,
						525
					],
					[
						40800,
						2,
						525
					],
					[
						41400,
						5,
						525
					],
					[
						41400,
						1,
						525
					]
				],
				"mustHitSection": false
			},
			{
				"lengthInSteps": 16,
				"sectionNotes": [
					[
						42000,
						4,
						525
					],
					[
						42600,
						7,
						525
					],
					[
						42000,
						0,
						525
					],
					[
						42600,
						3,
						525
					]
				],
				"mustHitSection": false
			},
			{
				"lengthInSteps": 16,
				"sectionNotes": [
					[
						43800,
						6,
						525
					],
					[
						43800,
						2,
						525
					]
				],
				"mustHitSection": true
			},
			{
				"lengthInSteps": 16,
				"sectionNotes": [
					[
						44400,
						4,
						525
					],
					[
						44400,
						0,
						525
					],
					[
						45000,
						1,
						375
					],
					[
						45000,
						5,
						375
					],
					[
						45450,
						7,
						525
					],
					[
						45450,
						3,
						525
					]
				],
				"mustHitSection": true
			},
			{
				"lengthInSteps": 16,
				"sectionNotes": [
					[
						46200,
						6,
						525
					],
					[
						46200,
						2,
						525
					]
				],
				"mustHitSection": false
			},
			{
				"lengthInSteps": 16,
				"sectionNotes": [
					[
						46800,
						4,
						525
					],
					[
						46800,
						0,
						525
					],
					[
						47400,
						1,
						75
					],
					[
						47400,
						5,
						75
					],
					[
						47850,
						7,
						525
					],
					[
						47850,
						3,
						525
					],
					[
						47700,
						5,
						0
					],
					[
						47700,
						1,
						0
					]
				],
				"mustHitSection": true
			},
			{
				"lengthInSteps": 16,
				"sectionNotes": [
					[
						48600,
						6,
						525
					],
					[
						48600,
						2,
						525
					]
				],
				"mustHitSection": true
			},
			{
				"lengthInSteps": 16,
				"sectionNotes": [
					[
						49200,
						5,
						525
					],
					[
						49200,
						1,
						525
					],
					[
						49800,
						4,
						525
					],
					[
						49800,
						0,
						525
					]
				],
				"mustHitSection": true
			},
			{
				"lengthInSteps": 16,
				"sectionNotes": [
					[
						50400,
						7,
						525
					],
					[
						50400,
						3,
						525
					],
					[
						51000,
						2,
						525
					],
					[
						51000,
						6,
						525
					]
				],
				"mustHitSection": true
			},
			{
				"lengthInSteps": 16,
				"sectionNotes": [
					[
						51600,
						4,
						525
					],
					[
						52200,
						5,
						525
					],
					[
						51600,
						0,
						525
					],
					[
						52200,
						1,
						525
					]
				],
				"mustHitSection": true
			},
			{
				"sectionNotes": [
					[
						52800,
						6,
						0
					],
					[
						52950,
						7,
						0
					],
					[
						53100,
						6,
						0
					],
					[
						53250,
						5,
						0
					],
					[
						53400,
						7,
						0
					],
					[
						53550,
						4,
						0
					],
					[
						53700,
						5,
						0
					],
					[
						53850,
						6,
						0
					]
				],
				"typeOfSection": 0,
				"lengthInSteps": 16,
				"altAnim": false,
				"mustHitSection": true,
				"changeBPM": false,
				"bpm": 110
			},
			{
				"sectionNotes": [
					[
						54000,
						7,
						0
					],
					[
						54150,
						6,
						0
					],
					[
						54300,
						5,
						0
					],
					[
						54450,
						4,
						0
					],
					[
						54600,
						5,
						0
					],
					[
						54750,
						7,
						0
					],
					[
						54900,
						4,
						0
					],
					[
						55050,
						6,
						0
					]
				],
				"typeOfSection": 0,
				"lengthInSteps": 16,
				"altAnim": false,
				"mustHitSection": true,
				"changeBPM": false,
				"bpm": 230
			},
			{
				"sectionNotes": [
					[
						55200,
						5,
						0
					],
					[
						55350,
						6,
						0
					],
					[
						55500,
						5,
						0
					],
					[
						55650,
						7,
						0
					],
					[
						55800,
						5,
						0
					],
					[
						55950,
						6,
						0
					],
					[
						56100,
						4,
						0
					],
					[
						56250,
						5,
						0
					]
				],
				"typeOfSection": 0,
				"lengthInSteps": 16,
				"altAnim": false,
				"mustHitSection": true,
				"changeBPM": false,
				"bpm": 230
			},
			{
				"sectionNotes": [
					[
						56400,
						6,
						0
					],
					[
						56550,
						7,
						0
					],
					[
						56700,
						4,
						0
					],
					[
						56850,
						6,
						0
					],
					[
						57000,
						7,
						0
					],
					[
						57150,
						5,
						0
					],
					[
						57300,
						4,
						0
					],
					[
						57450,
						5,
						0
					]
				],
				"typeOfSection": 0,
				"lengthInSteps": 16,
				"altAnim": false,
				"mustHitSection": true,
				"changeBPM": false,
				"bpm": 230
			},
			{
				"sectionNotes": [
					[
						57600,
						7,
						0
					],
					[
						57750,
						6,
						0
					],
					[
						57900,
						5,
						0
					],
					[
						58050,
						6,
						0
					],
					[
						58200,
						7,
						0
					],
					[
						58350,
						4,
						0
					],
					[
						58500,
						5,
						0
					],
					[
						58650,
						6,
						0
					]
				],
				"typeOfSection": 0,
				"lengthInSteps": 16,
				"altAnim": false,
				"mustHitSection": true,
				"changeBPM": false,
				"bpm": 230
			},
			{
				"sectionNotes": [
					[
						58800,
						5,
						0
					],
					[
						58950,
						6,
						0
					],
					[
						59100,
						4,
						0
					],
					[
						59250,
						5,
						0
					],
					[
						59400,
						7,
						0
					],
					[
						59550,
						6,
						0
					],
					[
						59700,
						5,
						0
					],
					[
						59850,
						6,
						0
					]
				],
				"typeOfSection": 0,
				"lengthInSteps": 16,
				"altAnim": false,
				"mustHitSection": true,
				"changeBPM": false,
				"bpm": 230
			},
			{
				"sectionNotes": [
					[
						60000,
						5,
						0
					],
					[
						60150,
						4,
						0
					],
					[
						60300,
						6,
						0
					],
					[
						60450,
						5,
						0
					],
					[
						60600,
						7,
						0
					],
					[
						60750,
						6,
						0
					],
					[
						60900,
						4,
						0
					],
					[
						61050,
						5,
						0
					]
				],
				"typeOfSection": 0,
				"lengthInSteps": 16,
				"altAnim": false,
				"mustHitSection": true,
				"changeBPM": false,
				"bpm": 230
			},
			{
				"sectionNotes": [
					[
						61200,
						6,
						0
					],
					[
						61350,
						5,
						0
					],
					[
						61500,
						6,
						0
					],
					[
						61650,
						7,
						0
					],
					[
						61800,
						6,
						0
					],
					[
						61950,
						4,
						0
					],
					[
						62100,
						7,
						0
					],
					[
						62250,
						6,
						0
					]
				],
				"typeOfSection": 0,
				"lengthInSteps": 16,
				"altAnim": false,
				"mustHitSection": true,
				"changeBPM": false,
				"bpm": 230
			},
			{
				"sectionNotes": [
					[
						62550,
						5,
						0
					],
					[
						62850,
						5,
						0
					],
					[
						63150,
						5,
						0
					],
					[
						63450,
						5,
						0
					]
				],
				"typeOfSection": 0,
				"lengthInSteps": 16,
				"altAnim": false,
				"mustHitSection": true,
				"changeBPM": false,
				"bpm": 230
			},
			{
				"sectionNotes": [
					[
						63600,
						3,
						0
					],
					[
						63750,
						2,
						0
					],
					[
						63900,
						1,
						0
					],
					[
						64050,
						0,
						0
					],
					[
						64200,
						1,
						0
					],
					[
						64350,
						3,
						0
					],
					[
						64500,
						0,
						0
					],
					[
						64650,
						2,
						0
					]
				],
				"typeOfSection": 0,
				"lengthInSteps": 16,
				"altAnim": false,
				"mustHitSection": true,
				"changeBPM": false,
				"bpm": 230
			},
			{
				"sectionNotes": [
					[
						64800,
						1,
						0
					],
					[
						64950,
						2,
						0
					],
					[
						65100,
						1,
						0
					],
					[
						65250,
						3,
						0
					],
					[
						65400,
						1,
						0
					],
					[
						65550,
						2,
						0
					],
					[
						65700,
						0,
						0
					],
					[
						65850,
						1,
						0
					]
				],
				"typeOfSection": 0,
				"lengthInSteps": 16,
				"altAnim": false,
				"mustHitSection": true,
				"changeBPM": false,
				"bpm": 230
			},
			{
				"sectionNotes": [
					[
						66000,
						2,
						0
					],
					[
						66150,
						3,
						0
					],
					[
						66300,
						0,
						0
					],
					[
						66450,
						2,
						0
					],
					[
						66600,
						3,
						0
					],
					[
						66750,
						1,
						0
					],
					[
						66900,
						0,
						0
					],
					[
						67050,
						1,
						0
					]
				],
				"typeOfSection": 0,
				"lengthInSteps": 16,
				"altAnim": false,
				"mustHitSection": true,
				"changeBPM": false,
				"bpm": 230
			},
			{
				"sectionNotes": [
					[
						67200,
						3,
						0
					],
					[
						67350,
						2,
						0
					],
					[
						67500,
						1,
						0
					],
					[
						67650,
						2,
						0
					],
					[
						67800,
						3,
						0
					],
					[
						67950,
						0,
						0
					],
					[
						68100,
						1,
						0
					],
					[
						68250,
						2,
						0
					]
				],
				"typeOfSection": 0,
				"lengthInSteps": 16,
				"altAnim": false,
				"mustHitSection": true,
				"changeBPM": false,
				"bpm": 230
			},
			{
				"sectionNotes": [
					[
						68400,
						1,
						0
					],
					[
						68550,
						2,
						0
					],
					[
						68700,
						0,
						0
					],
					[
						68850,
						1,
						0
					],
					[
						69000,
						3,
						0
					],
					[
						69150,
						2,
						0
					],
					[
						69300,
						1,
						0
					],
					[
						69450,
						2,
						0
					]
				],
				"typeOfSection": 0,
				"lengthInSteps": 16,
				"altAnim": false,
				"mustHitSection": true,
				"changeBPM": false,
				"bpm": 230
			},
			{
				"sectionNotes": [
					[
						69600,
						1,
						0
					],
					[
						69750,
						0,
						0
					],
					[
						69900,
						2,
						0
					],
					[
						70050,
						1,
						0
					],
					[
						70200,
						3,
						0
					],
					[
						70350,
						2,
						0
					],
					[
						70500,
						0,
						0
					],
					[
						70650,
						1,
						0
					]
				],
				"typeOfSection": 0,
				"lengthInSteps": 16,
				"altAnim": false,
				"mustHitSection": true,
				"changeBPM": false,
				"bpm": 230
			},
			{
				"sectionNotes": [
					[
						70800,
						2,
						0
					],
					[
						70950,
						1,
						0
					],
					[
						71100,
						2,
						0
					],
					[
						71250,
						3,
						0
					],
					[
						71400,
						2,
						0
					],
					[
						71550,
						0,
						0
					],
					[
						71700,
						3,
						0
					],
					[
						71850,
						2,
						0
					],
					[
						70950,
						6,
						0
					],
					[
						71100,
						6,
						0
					],
					[
						71400,
						7,
						0
					],
					[
						71700,
						7,
						0
					]
				],
				"typeOfSection": 0,
				"lengthInSteps": 16,
				"altAnim": false,
				"mustHitSection": true,
				"changeBPM": false,
				"bpm": 230
			},
			{
				"sectionNotes": [
					[
						72000,
						7,
						0
					],
					[
						72300,
						7,
						0
					],
					[
						72600,
						7,
						0
					],
					[
						72750,
						6,
						0
					],
					[
						72900,
						7,
						0
					],
					[
						72000,
						1,
						0
					],
					[
						72150,
						2,
						0
					],
					[
						72300,
						3,
						0
					],
					[
						72450,
						2,
						0
					],
					[
						72600,
						1,
						0
					],
					[
						72750,
						0,
						0
					],
					[
						72900,
						1,
						0
					],
					[
						73050,
						2,
						0
					]
				],
				"typeOfSection": 0,
				"lengthInSteps": 16,
				"altAnim": false,
				"mustHitSection": true,
				"changeBPM": false,
				"bpm": 230
			},
			{
				"sectionNotes": [
					[
						73200,
						3,
						0
					],
					[
						73350,
						7,
						0
					],
					[
						73500,
						4,
						0
					],
					[
						73650,
						7,
						0
					],
					[
						73800,
						6,
						525
					],
					[
						73350,
						3,
						0
					],
					[
						73500,
						0,
						0
					],
					[
						73650,
						3,
						0
					],
					[
						73800,
						2,
						525
					]
				],
				"typeOfSection": 0,
				"lengthInSteps": 16,
				"altAnim": false,
				"mustHitSection": true,
				"changeBPM": false,
				"bpm": 230
			},
			{
				"sectionNotes": [
					[
						74550,
						4,
						0
					],
					[
						74550,
						0,
						0
					],
					[
						74700,
						5,
						0
					],
					[
						74700,
						1,
						0
					],
					[
						74850,
						6,
						0
					],
					[
						74850,
						2,
						0
					],
					[
						75000,
						7,
						375
					],
					[
						75000,
						3,
						375
					]
				],
				"typeOfSection": 0,
				"lengthInSteps": 16,
				"altAnim": false,
				"mustHitSection": true,
				"changeBPM": false,
				"bpm": 230
			},
			{
				"sectionNotes": [
					[
						75900,
						0,
						0
					],
					[
						76050,
						3,
						0
					],
					[
						76200,
						2,
						0
					],
					[
						76350,
						1,
						0
					],
					[
						76500,
						0,
						0
					],
					[
						76650,
						2,
						0
					],
					[
						75750,
						2,
						0
					],
					[
						75750,
						6,
						0
					],
					[
						75900,
						4,
						0
					],
					[
						76050,
						7,
						0
					],
					[
						76200,
						6,
						0
					],
					[
						76350,
						5,
						0
					],
					[
						76500,
						4,
						0
					],
					[
						76650,
						6,
						0
					]
				],
				"typeOfSection": 0,
				"lengthInSteps": 16,
				"altAnim": false,
				"mustHitSection": true,
				"changeBPM": false,
				"bpm": 230
			},
			{
				"sectionNotes": [
					[
						76800,
						7,
						0
					],
					[
						76950,
						4,
						0
					],
					[
						77250,
						6,
						0
					],
					[
						77400,
						5,
						375
					],
					[
						76800,
						3,
						0
					],
					[
						76950,
						0,
						0
					],
					[
						77250,
						2,
						0
					],
					[
						77400,
						1,
						375
					]
				],
				"typeOfSection": 0,
				"lengthInSteps": 16,
				"altAnim": false,
				"mustHitSection": true,
				"changeBPM": false,
				"bpm": 230
			},
			{
				"sectionNotes": [
					[
						78150,
						3,
						0
					],
					[
						78150,
						7,
						0
					],
					[
						78300,
						2,
						0
					],
					[
						78300,
						6,
						0
					],
					[
						78450,
						3,
						0
					],
					[
						78450,
						7,
						0
					],
					[
						78600,
						0,
						0
					],
					[
						78600,
						4,
						0
					],
					[
						78750,
						1,
						0
					],
					[
						78750,
						5,
						0
					],
					[
						78900,
						3,
						0
					],
					[
						78900,
						7,
						0
					],
					[
						79050,
						2,
						0
					],
					[
						79050,
						6,
						0
					]
				],
				"typeOfSection": 0,
				"lengthInSteps": 16,
				"altAnim": false,
				"mustHitSection": true,
				"changeBPM": false,
				"bpm": 230
			},
			{
				"sectionNotes": [
					[
						79200,
						4,
						300
					],
					[
						79200,
						0,
						300
					],
					[
						79650,
						6,
						0
					],
					[
						79650,
						2,
						0
					],
					[
						79800,
						7,
						0
					],
					[
						79800,
						3,
						0
					],
					[
						79950,
						4,
						0
					],
					[
						79950,
						0,
						0
					],
					[
						80250,
						5,
						0
					]
				],
				"typeOfSection": 0,
				"lengthInSteps": 16,
				"altAnim": false,
				"mustHitSection": true,
				"changeBPM": false,
				"bpm": 230
			},
			{
				"sectionNotes": [
					[
						80550,
						2,
						0
					],
					[
						80550,
						6,
						0
					],
					[
						80700,
						1,
						0
					],
					[
						80700,
						5,
						0
					],
					[
						80850,
						2,
						0
					],
					[
						80850,
						6,
						0
					],
					[
						81000,
						0,
						0
					],
					[
						81000,
						4,
						0
					],
					[
						81150,
						3,
						0
					],
					[
						81150,
						7,
						0
					],
					[
						81300,
						2,
						0
					],
					[
						81300,
						6,
						0
					],
					[
						81450,
						5,
						0
					]
				],
				"typeOfSection": 0,
				"lengthInSteps": 16,
				"altAnim": false,
				"mustHitSection": true,
				"changeBPM": false,
				"bpm": 230
			},
			{
				"sectionNotes": [
					[
						81600,
						4,
						0
					],
					[
						81750,
						7,
						0
					],
					[
						82050,
						6,
						0
					],
					[
						82200,
						5,
						525
					]
				],
				"typeOfSection": 0,
				"lengthInSteps": 16,
				"altAnim": false,
				"mustHitSection": true,
				"changeBPM": false,
				"bpm": 230
			},
			{
				"sectionNotes": [],
				"typeOfSection": 0,
				"lengthInSteps": 16,
				"altAnim": false,
				"mustHitSection": true,
				"changeBPM": false,
				"bpm": 230
			},
			{
				"sectionNotes": [],
				"typeOfSection": 0,
				"lengthInSteps": 16,
				"altAnim": false,
				"mustHitSection": true,
				"changeBPM": false,
				"bpm": 230
			},
			{
				"sectionNotes": [],
				"typeOfSection": 0,
				"lengthInSteps": 16,
				"altAnim": false,
				"mustHitSection": true,
				"changeBPM": false,
				"bpm": 230
			},
			{
				"sectionNotes": [],
				"typeOfSection": 0,
				"lengthInSteps": 16,
				"altAnim": false,
				"mustHitSection": true,
				"changeBPM": false,
				"bpm": 230
			},
			{
				"sectionNotes": [],
				"typeOfSection": 0,
				"lengthInSteps": 16,
				"altAnim": false,
				"mustHitSection": true,
				"changeBPM": false,
				"bpm": 230
			},
			{
				"sectionNotes": [],
				"typeOfSection": 0,
				"lengthInSteps": 16,
				"altAnim": false,
				"mustHitSection": true,
				"changeBPM": false,
				"bpm": 230
			},
			{
				"sectionNotes": [],
				"typeOfSection": 0,
				"lengthInSteps": 16,
				"altAnim": false,
				"mustHitSection": true,
				"changeBPM": false,
				"bpm": 230
			},
			{
				"sectionNotes": [],
				"typeOfSection": 0,
				"lengthInSteps": 16,
				"altAnim": false,
				"mustHitSection": true,
				"changeBPM": false,
				"bpm": 230
			},
			{
				"sectionNotes": [],
				"typeOfSection": 0,
				"lengthInSteps": 16,
				"altAnim": false,
				"mustHitSection": true,
				"changeBPM": false,
				"bpm": 230
			},
			{
				"sectionNotes": [],
				"typeOfSection": 0,
				"lengthInSteps": 16,
				"altAnim": false,
				"mustHitSection": true,
				"changeBPM": false,
				"bpm": 230
			},
			{
				"sectionNotes": [],
				"typeOfSection": 0,
				"lengthInSteps": 16,
				"altAnim": false,
				"mustHitSection": true,
				"changeBPM": false,
				"bpm": 230
			},
			{
				"sectionNotes": [],
				"typeOfSection": 0,
				"lengthInSteps": 16,
				"altAnim": false,
				"mustHitSection": true,
				"changeBPM": false,
				"bpm": 230
			},
			{
				"sectionNotes": [],
				"typeOfSection": 0,
				"lengthInSteps": 16,
				"altAnim": false,
				"mustHitSection": true,
				"changeBPM": false,
				"bpm": 230
			},
			{
				"sectionNotes": [],
				"typeOfSection": 0,
				"lengthInSteps": 16,
				"altAnim": false,
				"mustHitSection": true,
				"changeBPM": false,
				"bpm": 230
			},
			{
				"sectionNotes": [],
				"typeOfSection": 0,
				"lengthInSteps": 16,
				"altAnim": false,
				"mustHitSection": true,
				"changeBPM": false,
				"bpm": 230
			},
			{
				"sectionNotes": [],
				"typeOfSection": 0,
				"lengthInSteps": 16,
				"altAnim": false,
				"mustHitSection": true,
				"changeBPM": false,
				"bpm": 230
			},
			{
				"sectionNotes": [],
				"typeOfSection": 0,
				"lengthInSteps": 16,
				"altAnim": false,
				"mustHitSection": true,
				"changeBPM": false,
				"bpm": 230
			},
			{
				"sectionNotes": [],
				"typeOfSection": 0,
				"lengthInSteps": 16,
				"altAnim": false,
				"mustHitSection": true,
				"changeBPM": false,
				"bpm": 230
			},
			{
				"sectionNotes": [],
				"typeOfSection": 0,
				"lengthInSteps": 16,
				"altAnim": false,
				"mustHitSection": true,
				"changeBPM": false,
				"bpm": 230
			},
			{
				"sectionNotes": [],
				"typeOfSection": 0,
				"lengthInSteps": 16,
				"altAnim": false,
				"mustHitSection": true,
				"changeBPM": false,
				"bpm": 230
			},
			{
				"sectionNotes": [],
				"typeOfSection": 0,
				"lengthInSteps": 16,
				"altAnim": false,
				"mustHitSection": true,
				"changeBPM": false,
				"bpm": 230
			},
			{
				"sectionNotes": [],
				"typeOfSection": 0,
				"lengthInSteps": 16,
				"altAnim": false,
				"mustHitSection": true,
				"changeBPM": false,
				"bpm": 230
			},
			{
				"sectionNotes": [],
				"typeOfSection": 0,
				"lengthInSteps": 16,
				"altAnim": false,
				"mustHitSection": true,
				"changeBPM": false,
				"bpm": 230
			},
			{
				"sectionNotes": [],
				"typeOfSection": 0,
				"lengthInSteps": 16,
				"altAnim": false,
				"mustHitSection": true,
				"changeBPM": false,
				"bpm": 230
			},
			{
				"sectionNotes": [],
				"typeOfSection": 0,
				"lengthInSteps": 16,
				"altAnim": false,
				"mustHitSection": true,
				"changeBPM": false,
				"bpm": 230
			},
			{
				"sectionNotes": [],
				"typeOfSection": 0,
				"lengthInSteps": 16,
				"altAnim": false,
				"mustHitSection": true,
				"changeBPM": false,
				"bpm": 230
			},
			{
				"sectionNotes": [],
				"typeOfSection": 0,
				"lengthInSteps": 16,
				"altAnim": false,
				"mustHitSection": true,
				"changeBPM": false,
				"bpm": 230
			},
			{
				"sectionNotes": [],
				"typeOfSection": 0,
				"lengthInSteps": 16,
				"altAnim": false,
				"mustHitSection": true,
				"changeBPM": false,
				"bpm": 230
			},
			{
				"sectionNotes": [],
				"typeOfSection": 0,
				"lengthInSteps": 16,
				"altAnim": false,
				"mustHitSection": true,
				"changeBPM": false,
				"bpm": 230
			},
			{
				"sectionNotes": [],
				"typeOfSection": 0,
				"lengthInSteps": 16,
				"altAnim": false,
				"mustHitSection": true,
				"changeBPM": false,
				"bpm": 230
			},
			{
				"sectionNotes": [],
				"typeOfSection": 0,
				"lengthInSteps": 16,
				"altAnim": false,
				"mustHitSection": true,
				"changeBPM": false,
				"bpm": 230
			},
			{
				"sectionNotes": [],
				"typeOfSection": 0,
				"lengthInSteps": 16,
				"altAnim": false,
				"mustHitSection": true,
				"changeBPM": false,
				"bpm": 230
			},
			{
				"sectionNotes": [],
				"typeOfSection": 0,
				"lengthInSteps": 16,
				"altAnim": false,
				"mustHitSection": true,
				"changeBPM": false,
				"bpm": 230
			},
			{
				"sectionNotes": [],
				"typeOfSection": 0,
				"lengthInSteps": 16,
				"altAnim": false,
				"mustHitSection": true,
				"changeBPM": false,
				"bpm": 230
			},
			{
				"sectionNotes": [],
				"typeOfSection": 0,
				"lengthInSteps": 16,
				"altAnim": false,
				"mustHitSection": true,
				"changeBPM": false,
				"bpm": 230
			},
			{
				"sectionNotes": [],
				"typeOfSection": 0,
				"lengthInSteps": 16,
				"altAnim": false,
				"mustHitSection": true,
				"changeBPM": false,
				"bpm": 230
			},
			{
				"sectionNotes": [],
				"typeOfSection": 0,
				"lengthInSteps": 16,
				"altAnim": false,
				"mustHitSection": true,
				"changeBPM": false,
				"bpm": 230
			},
			{
				"sectionNotes": [],
				"typeOfSection": 0,
				"lengthInSteps": 16,
				"altAnim": false,
				"mustHitSection": true,
				"changeBPM": false,
				"bpm": 230
			},
			{
				"sectionNotes": [],
				"typeOfSection": 0,
				"lengthInSteps": 16,
				"altAnim": false,
				"mustHitSection": true,
				"changeBPM": false,
				"bpm": 230
			},
			{
				"sectionNotes": [],
				"typeOfSection": 0,
				"lengthInSteps": 16,
				"altAnim": false,
				"mustHitSection": true,
				"changeBPM": false,
				"bpm": 230
			},
			{
				"sectionNotes": [],
				"typeOfSection": 0,
				"lengthInSteps": 16,
				"altAnim": false,
				"mustHitSection": true,
				"changeBPM": false,
				"bpm": 230
			},
			{
				"sectionNotes": [],
				"typeOfSection": 0,
				"lengthInSteps": 16,
				"altAnim": false,
				"mustHitSection": true,
				"changeBPM": false,
				"bpm": 230
			},
			{
				"sectionNotes": [],
				"typeOfSection": 0,
				"lengthInSteps": 16,
				"altAnim": false,
				"mustHitSection": true,
				"changeBPM": false,
				"bpm": 230
			},
			{
				"sectionNotes": [],
				"typeOfSection": 0,
				"lengthInSteps": 16,
				"altAnim": false,
				"mustHitSection": true,
				"changeBPM": false,
				"bpm": 230
			},
			{
				"sectionNotes": [],
				"typeOfSection": 0,
				"lengthInSteps": 16,
				"altAnim": false,
				"mustHitSection": true,
				"changeBPM": false,
				"bpm": 230
			},
			{
				"sectionNotes": [],
				"typeOfSection": 0,
				"lengthInSteps": 16,
				"altAnim": false,
				"mustHitSection": true,
				"changeBPM": false,
				"bpm": 230
			},
			{
				"sectionNotes": [],
				"typeOfSection": 0,
				"lengthInSteps": 16,
				"altAnim": false,
				"mustHitSection": true,
				"changeBPM": false,
				"bpm": 230
			},
			{
				"sectionNotes": [],
				"typeOfSection": 0,
				"lengthInSteps": 16,
				"altAnim": false,
				"mustHitSection": true,
				"changeBPM": false,
				"bpm": 230
			},
			{
				"sectionNotes": [],
				"typeOfSection": 0,
				"lengthInSteps": 16,
				"altAnim": false,
				"mustHitSection": true,
				"changeBPM": false,
				"bpm": 230
			},
			{
				"sectionNotes": [],
				"typeOfSection": 0,
				"lengthInSteps": 16,
				"altAnim": false,
				"mustHitSection": true,
				"changeBPM": false,
				"bpm": 230
			},
			{
				"sectionNotes": [],
				"typeOfSection": 0,
				"lengthInSteps": 16,
				"altAnim": false,
				"mustHitSection": true,
				"changeBPM": false,
				"bpm": 230
			},
			{
				"sectionNotes": [],
				"typeOfSection": 0,
				"lengthInSteps": 16,
				"altAnim": false,
				"mustHitSection": true,
				"changeBPM": false,
				"bpm": 230
			},
			{
				"sectionNotes": [],
				"typeOfSection": 0,
				"lengthInSteps": 16,
				"altAnim": false,
				"mustHitSection": true,
				"changeBPM": false,
				"bpm": 230
			},
			{
				"sectionNotes": [],
				"typeOfSection": 0,
				"lengthInSteps": 16,
				"altAnim": false,
				"mustHitSection": true,
				"changeBPM": false,
				"bpm": 230
			},
			{
				"sectionNotes": [],
				"typeOfSection": 0,
				"lengthInSteps": 16,
				"altAnim": false,
				"mustHitSection": true,
				"changeBPM": false,
				"bpm": 230
			},
			{
				"sectionNotes": [],
				"typeOfSection": 0,
				"lengthInSteps": 16,
				"altAnim": false,
				"mustHitSection": true,
				"changeBPM": false,
				"bpm": 230
			},
			{
				"sectionNotes": [],
				"typeOfSection": 0,
				"lengthInSteps": 16,
				"altAnim": false,
				"mustHitSection": true,
				"changeBPM": false,
				"bpm": 230
			},
			{
				"sectionNotes": [],
				"typeOfSection": 0,
				"lengthInSteps": 16,
				"altAnim": false,
				"mustHitSection": true,
				"changeBPM": false,
				"bpm": 230
			},
			{
				"sectionNotes": [],
				"typeOfSection": 0,
				"lengthInSteps": 16,
				"altAnim": false,
				"mustHitSection": true,
				"changeBPM": false,
				"bpm": 230
			},
			{
				"sectionNotes": [],
				"typeOfSection": 0,
				"lengthInSteps": 16,
				"altAnim": false,
				"mustHitSection": true,
				"changeBPM": false,
				"bpm": 230
			},
			{
				"sectionNotes": [],
				"typeOfSection": 0,
				"lengthInSteps": 16,
				"altAnim": false,
				"mustHitSection": true,
				"changeBPM": false,
				"bpm": 230
			},
			{
				"sectionNotes": [],
				"typeOfSection": 0,
				"lengthInSteps": 16,
				"altAnim": false,
				"mustHitSection": true,
				"changeBPM": false,
				"bpm": 230
			},
			{
				"sectionNotes": [],
				"typeOfSection": 0,
				"lengthInSteps": 16,
				"altAnim": false,
				"mustHitSection": true,
				"changeBPM": false,
				"bpm": 230
			},
			{
				"sectionNotes": [],
				"typeOfSection": 0,
				"lengthInSteps": 16,
				"altAnim": false,
				"mustHitSection": true,
				"changeBPM": false,
				"bpm": 230
			},
			{
				"sectionNotes": [],
				"typeOfSection": 0,
				"lengthInSteps": 16,
				"altAnim": false,
				"mustHitSection": true,
				"changeBPM": false,
				"bpm": 230
			},
			{
				"sectionNotes": [],
				"typeOfSection": 0,
				"lengthInSteps": 16,
				"altAnim": false,
				"mustHitSection": true,
				"changeBPM": false,
				"bpm": 230
			},
			{
				"sectionNotes": [],
				"typeOfSection": 0,
				"lengthInSteps": 16,
				"altAnim": false,
				"mustHitSection": true,
				"changeBPM": false,
				"bpm": 230
			},
			{
				"sectionNotes": [],
				"typeOfSection": 0,
				"lengthInSteps": 16,
				"altAnim": false,
				"mustHitSection": true,
				"changeBPM": false,
				"bpm": 230
			},
			{
				"sectionNotes": [],
				"typeOfSection": 0,
				"lengthInSteps": 16,
				"altAnim": false,
				"mustHitSection": true,
				"changeBPM": false,
				"bpm": 230
			},
			{
				"sectionNotes": [],
				"typeOfSection": 0,
				"lengthInSteps": 16,
				"altAnim": false,
				"mustHitSection": true,
				"changeBPM": false,
				"bpm": 230
			},
			{
				"sectionNotes": [],
				"typeOfSection": 0,
				"lengthInSteps": 16,
				"altAnim": false,
				"mustHitSection": true,
				"changeBPM": false,
				"bpm": 230
			},
			{
				"sectionNotes": [],
				"typeOfSection": 0,
				"lengthInSteps": 16,
				"altAnim": false,
				"mustHitSection": true,
				"changeBPM": false,
				"bpm": 230
			},
			{
				"sectionNotes": [],
				"typeOfSection": 0,
				"lengthInSteps": 16,
				"altAnim": false,
				"mustHitSection": true,
				"changeBPM": false,
				"bpm": 230
			},
			{
				"sectionNotes": [],
				"typeOfSection": 0,
				"lengthInSteps": 16,
				"altAnim": false,
				"mustHitSection": true,
				"changeBPM": false,
				"bpm": 230
			},
			{
				"sectionNotes": [],
				"typeOfSection": 0,
				"lengthInSteps": 16,
				"altAnim": false,
				"mustHitSection": true,
				"changeBPM": false,
				"bpm": 230
			},
			{
				"sectionNotes": [],
				"typeOfSection": 0,
				"lengthInSteps": 16,
				"altAnim": false,
				"mustHitSection": true,
				"changeBPM": false,
				"bpm": 230
			},
			{
				"sectionNotes": [],
				"typeOfSection": 0,
				"lengthInSteps": 16,
				"altAnim": false,
				"mustHitSection": true,
				"changeBPM": false,
				"bpm": 230
			},
			{
				"sectionNotes": [],
				"typeOfSection": 0,
				"lengthInSteps": 16,
				"altAnim": false,
				"mustHitSection": true,
				"changeBPM": false,
				"bpm": 230
			},
			{
				"sectionNotes": [],
				"typeOfSection": 0,
				"lengthInSteps": 16,
				"altAnim": false,
				"mustHitSection": true,
				"changeBPM": false,
				"bpm": 230
			},
			{
				"lengthInSteps": 16,
				"typeOfSection": 0,
				"sectionNotes": [],
				"altAnim": false,
				"bpm": 230,
				"changeBPM": false,
				"mustHitSection": true
			},
			{
				"lengthInSteps": 16,
				"typeOfSection": 0,
				"sectionNotes": [],
				"altAnim": false,
				"bpm": 230,
				"changeBPM": false,
				"mustHitSection": true
			},
			{
				"lengthInSteps": 16,
				"typeOfSection": 0,
				"sectionNotes": [],
				"altAnim": false,
				"bpm": 230,
				"changeBPM": false,
				"mustHitSection": true
			},
			{
				"lengthInSteps": 16,
				"typeOfSection": 0,
				"sectionNotes": [],
				"altAnim": false,
				"bpm": 230,
				"changeBPM": false,
				"mustHitSection": true
			},
			{
				"lengthInSteps": 16,
				"typeOfSection": 0,
				"sectionNotes": [],
				"altAnim": false,
				"bpm": 230,
				"changeBPM": false,
				"mustHitSection": true
			},
			{
				"lengthInSteps": 16,
				"typeOfSection": 0,
				"sectionNotes": [],
				"altAnim": false,
				"bpm": 230,
				"changeBPM": false,
				"mustHitSection": true
			},
			{
				"sectionNotes": [],
				"typeOfSection": 0,
				"lengthInSteps": 16,
				"altAnim": false,
				"mustHitSection": true,
				"changeBPM": false,
				"bpm": 230
			},
			{
				"lengthInSteps": 16,
				"typeOfSection": 0,
				"sectionNotes": [],
				"altAnim": false,
				"bpm": 230,
				"changeBPM": false,
				"mustHitSection": true
			},
			{
				"lengthInSteps": 16,
				"typeOfSection": 0,
				"sectionNotes": [],
				"altAnim": false,
				"bpm": 230,
				"changeBPM": false,
				"mustHitSection": true
			},
			{
				"sectionNotes": [],
				"typeOfSection": 0,
				"lengthInSteps": 16,
				"altAnim": false,
				"mustHitSection": true,
				"changeBPM": false,
				"bpm": 230
			},
			{
				"sectionNotes": [],
				"typeOfSection": 0,
				"lengthInSteps": 16,
				"altAnim": false,
				"mustHitSection": true,
				"changeBPM": false,
				"bpm": 230
			},
			{
				"sectionNotes": [],
				"typeOfSection": 0,
				"lengthInSteps": 16,
				"altAnim": false,
				"mustHitSection": true,
				"changeBPM": false,
				"bpm": 230
			},
			{
				"sectionNotes": [],
				"typeOfSection": 0,
				"lengthInSteps": 16,
				"altAnim": false,
				"mustHitSection": true,
				"changeBPM": false,
				"bpm": 230
			},
			{
				"sectionNotes": [],
				"typeOfSection": 0,
				"lengthInSteps": 16,
				"altAnim": false,
				"mustHitSection": true,
				"changeBPM": false,
				"bpm": 230
			},
			{
				"sectionNotes": [],
				"typeOfSection": 0,
				"lengthInSteps": 16,
				"altAnim": false,
				"mustHitSection": true,
				"changeBPM": false,
				"bpm": 230
			},
			{
				"sectionNotes": [],
				"typeOfSection": 0,
				"lengthInSteps": 16,
				"altAnim": false,
				"mustHitSection": true,
				"changeBPM": false,
				"bpm": 230
			},
			{
				"lengthInSteps": 16,
				"altAnim": false,
				"typeOfSection": 0,
				"sectionNotes": [],
				"bpm": 230,
				"changeBPM": false,
				"mustHitSection": true
			}
		],
		"player3": "gf",
		"song": "milkyways",
		"stage": "baseplatereal",
		"needsVoices": true,
		"validScore": true,
		"speed": 3.5,
		"bpm": 200
	}
}